AppGenerator/__init__.py
AppGenerator/asgi.py
AppGenerator/settings.py
AppGenerator/urls.py
AppGenerator/wsgi.py
app/__init__.py
app/apps.py
app/models.py
app/tests.py
app/views.py
app/fields/__init__.py
app/fields/test_model.py
app/fields/test_model_related.py
app/migrations/0001_initial.py
app/migrations/__init__.py
django_model_suite/__init__.py
django_model_suite/admin.py
django_model_suite/apps.py
django_model_suite/generators/__init__.py
django_model_suite/generators/base.py
django_model_suite/generators/model_utils.py
django_model_suite/generators/admin/__init__.py
django_model_suite/generators/admin/admin_generator.py
django_model_suite/generators/admin/change_view_generator.py
django_model_suite/generators/admin/context_generator.py
django_model_suite/generators/admin/display_generator.py
django_model_suite/generators/admin/inline.py
django_model_suite/generators/admin/list_view_generator.py
django_model_suite/generators/admin/permissions_generator.py
django_model_suite/generators/admin/resource_generator.py
django_model_suite/generators/api/__init__.py
django_model_suite/generators/api/filter_generator.py
django_model_suite/generators/api/pagination_generator.py
django_model_suite/generators/api/serializer_generator.py
django_model_suite/generators/api/url_generator.py
django_model_suite/generators/api/view_generator.py
django_model_suite/generators/domain/__init__.py
django_model_suite/generators/domain/selector_generator.py
django_model_suite/generators/domain/service_generator.py
django_model_suite/generators/domain/validator_generator.py
django_model_suite/generators/field/__init__.py
django_model_suite/generators/field/fields_generator.py
django_model_suite/management/__init__.py
django_model_suite/management/commands/__init__.py
django_model_suite/management/commands/generate_files.py
django_model_suite/migrations/__init__.py
django_model_suite-0.1.19.dist-info/METADATA
django_model_suite-0.1.19.dist-info/WHEEL
django_model_suite-0.1.19.dist-info/top_level.txt
django_model_suite-0.1.19.dist-info/RECORD
