Metadata-Version: 2.4
Name: django_model_suite
Version: 0.1.19
Summary: A Django app for generating boilerplate code
Home-page: https://github.com/omargawdat/django-model-suite
Author: Omar Gawdat
Author-email: omargawdaat@gmail.com
Classifier: Development Status :: 3 - Alpha
Classifier: Environment :: Web Environment
Classifier: Framework :: Django
Classifier: Intended Audience :: Developers
Classifier: License :: OSI Approved :: MIT License
Classifier: Operating System :: OS Independent
Classifier: Programming Language :: Python :: 3.9
Classifier: Programming Language :: Python :: 3.10
Classifier: Programming Language :: Python :: 3.11
Requires-Python: >=3.8
Requires-Dist: Django>=5.0
Requires-Dist: django-unfold>=0.45.0
Requires-Dist: djangorestframework>=3.14.0
Requires-Dist: django-filter>=23.0
Dynamic: author
Dynamic: author-email
Dynamic: classifier
Dynamic: description
Dynamic: description-content-type
Dynamic: home-page
Dynamic: requires-dist
Dynamic: requires-python
Dynamic: summary
